{
  "project_info": {
    "project_number": "191405085984",
    "project_id": "myatecommerce",
    "storage_bucket": "myatecommerce.firebasestorage.app"
  },
  "client": [
    {
      "client_info": {
        "mobilesdk_app_id": "1:191405085984:android:c8fb393753112ffcbcb345",
        "android_client_info": {
          "package_name": "app.com.mm.myat_ecommerence"
        }
      },
      "oauth_client": [],
      "api_key": [
        {
          "current_key": "AIzaSyA5E4uEp0E_7svv-G4jl7OHAuxFNXg33wY"
        }
      ],
      "services": {
        "appinvite_service": {
          "other_platform_oauth_client": []
        }
      }
    }
  ],
  "configuration_version": "1"
}